samexporter/__init__.py
samexporter/export_decoder.py
samexporter/export_encoder.py
samexporter/export_sam2.py
samexporter/inference.py
samexporter/onnx_utils.py
samexporter/sam2_onnx.py
samexporter/sam_onnx.py
samexporter-0.4.1.dist-info/LICENSE
samexporter-0.4.1.dist-info/METADATA
samexporter-0.4.1.dist-info/WHEEL
samexporter-0.4.1.dist-info/top_level.txt
samexporter-0.4.1.dist-info/RECORD
