Metadata-Version: 2.1
Name: samexporter
Version: 0.4.1
Summary: Exporting Segment Anything models ONNX format
Author-email: Viet Anh Nguyen <vietanh.dev@gmail.com>
License: MIT License
Project-URL: Homepage, https://github.com/vietanhdev/samexporter
Project-URL: Bug Tracker, https://github.com/vietanhdev/samexporter/issues
Classifier: Programming Language :: Python :: 3
Classifier: License :: OSI Approved :: MIT License
Classifier: Operating System :: OS Independent
Requires-Python: >=3.10
License-File: LICENSE
Requires-Dist: onnx ==1.16.2
Requires-Dist: onnxruntime ==1.16.3
Requires-Dist: opencv-python ==4.7.0.72
Requires-Dist: segment-anything ==1.0
Requires-Dist: torch ==2.4.0
Requires-Dist: torchvision
Requires-Dist: timm ==0.9.2
Requires-Dist: onnxsim ==0.4.36
Provides-Extra: dev
Requires-Dist: flake8 ; extra == 'dev'
Requires-Dist: isort ; extra == 'dev'
Requires-Dist: black ; extra == 'dev'
Requires-Dist: pre-commit ; extra == 'dev'
